README.rst
setup.py
Druid.egg-info/PKG-INFO
Druid.egg-info/SOURCES.txt
Druid.egg-info/dependency_links.txt
Druid.egg-info/requires.txt
Druid.egg-info/top_level.txt
druid/__init__.py
druid/bootstrap.py
druid/druid.py
druid/image.py